setup.py
appml/__init__.py
appml/feat_imp.py
appml/grid_search.py
appml/viz.py
appml/xval.py
appml.egg-info/PKG-INFO
appml.egg-info/SOURCES.txt
appml.egg-info/dependency_links.txt
appml.egg-info/not-zip-safe
appml.egg-info/requires.txt
appml.egg-info/top_level.txt