Metadata-Version: 1.0
Name: appml
Version: 0.1
Summary: ml fucntions for training
Home-page: https://github.com/Jiannan28/appml
Author: Jiannan (Leo) Liu
Author-email: jiannan.liu.28@gmail.com
License: MIT
Platform: UNKNOWN
